polycutter/__init__.py
polycutter/__main__.py
polycutter/cli.py
polycutter/scene_detector.py
polycutter/segment_parser.py
polycutter/util/__init__.py
polycutter/util/formatting.py
polycutter/util/fs.py
polycutter/util/probe.py
polycutter/video_cutter.py
polycutter-0.5.0.dist-info/METADATA
polycutter-0.5.0.dist-info/WHEEL
polycutter-0.5.0.dist-info/entry_points.txt
polycutter-0.5.0.dist-info/RECORD
