Metadata-Version: 2.4
Name: polycutter
Version: 0.5.0
Summary: 
Author: user
Author-email: user@example.com
Requires-Python: >=3.9,<4.0
Classifier: Programming Language :: Python :: 3
Classifier: Programming Language :: Python :: 3.9
Classifier: Programming Language :: Python :: 3.10
Classifier: Programming Language :: Python :: 3.11
Classifier: Programming Language :: Python :: 3.12
Classifier: Programming Language :: Python :: 3.13
Classifier: Programming Language :: Python :: 3.14
Requires-Dist: redlog-py (>=0.1.1,<0.2.0)
Requires-Dist: sh (>=2.2.2,<3.0.0)
Requires-Dist: typer (>=0.20.0,<0.21.0)
